README.md
setup.py
edback/__init__.py
edback/cli.py
edback/exceptions.py
edback.egg-info/PKG-INFO
edback.egg-info/SOURCES.txt
edback.egg-info/dependency_links.txt
edback.egg-info/entry_points.txt
edback.egg-info/requires.txt
edback.egg-info/top_level.txt
edback/commands/__init__.py
edback/commands/cmd_backups.py
edback/commands/cmd_keys.py
edback/commands/backups/__init__.py
edback/commands/backups/cmd_create.py
edback/commands/backups/cmd_list.py
edback/commands/backups/cmd_remove.py
edback/commands/backups/cmd_revert.py
edback/commands/keys/__init__.py
edback/commands/keys/cmd_create.py
edback/commands/keys/cmd_export.py
edback/commands/keys/cmd_import.py
edback/commands/keys/cmd_list.py
edback/commands/keys/cmd_remove.py
edback/managers/__init__.py
edback/managers/backup.py
edback/managers/base.py
edback/managers/key.py
edback/managers/resource.py
edback/managers/storage.py
edback/structures/__init__.py
edback/structures/backup.py
edback/structures/key.py
edback/structures/object.py
edback/structures/storage.py
edback/utils/__init__.py
edback/utils/checksum.py
edback/utils/cipher.py
edback/utils/cli.py
edback/utils/echo.py
edback/utils/style.py
edback/utils/type.py
tests/__init__.py
tests/conftest.py
tests/managers/__init__.py
tests/managers/test_backup.py
tests/managers/test_base.py
tests/managers/test_key.py
tests/managers/test_storage.py
tests/structures/__init__.py
tests/structures/test_backup.py
tests/structures/test_key.py
tests/structures/test_object.py
tests/structures/test_storage.py
tests/utils/__init__.py
tests/utils/test_checksum.py
tests/utils/test_type.py