Metadata-Version: 1.1
Name: edback
Version: 0.1.3
Summary: Simple encrypt, decrypt, backup console application
Home-page: https://moreal.kr/~edback
Author: moreal
Author-email: dev.moreal@gmail.com
License: UNKNOWN
Platform: UNKNOWN
Classifier: Development Status :: 3 - Alpha
Classifier: Environment :: Console
Classifier: Intended Audience :: End Users/Desktop
Classifier: Programming Language :: Python :: 3.6
Classifier: Operating System :: POSIX
Classifier: Topic :: Utilities
